st_compare_stock/__init__.py
st_compare_stock/frontend/build/asset-manifest.json
st_compare_stock/frontend/build/bootstrap.min.css
st_compare_stock/frontend/build/index.html
st_compare_stock/frontend/build/precache-manifest.b7ac78e3903e47e9f7dd2745a79bfba4.js
st_compare_stock/frontend/build/service-worker.js
st_compare_stock/frontend/build/static/js/2.a6b6baee.chunk.js
st_compare_stock/frontend/build/static/js/2.a6b6baee.chunk.js.LICENSE.txt
st_compare_stock/frontend/build/static/js/2.a6b6baee.chunk.js.map
st_compare_stock/frontend/build/static/js/main.b4eb2086.chunk.js
st_compare_stock/frontend/build/static/js/main.b4eb2086.chunk.js.map
st_compare_stock/frontend/build/static/js/runtime-main.e691ffc4.js
st_compare_stock/frontend/build/static/js/runtime-main.e691ffc4.js.map
st_compare_stock-0.0.6.dist-info/LICENSE
st_compare_stock-0.0.6.dist-info/METADATA
st_compare_stock-0.0.6.dist-info/WHEEL
st_compare_stock-0.0.6.dist-info/top_level.txt
st_compare_stock-0.0.6.dist-info/RECORD
