Metadata-Version: 2.1
Name: st-compare-stock
Version: 0.0.6
Summary: This package provides a comparison component for stocks in Streamlit
Home-page: https://github.com/MihaiBlebea/streamlit_compare_stock
Author: Mihai Blebea
Author-email: mihaiserban.blebea@gmail.com
License: UNKNOWN
Platform: UNKNOWN
Requires-Python: >=3.6
License-File: LICENSE
Requires-Dist: streamlit (>=0.63)
